{"cameraMode":{"drawMode":0,"name":"Shaded","section":"Shading Mode"},"sceneLighting":false,"audioPlay":false,"sceneViewState":{"m_AlwaysRefresh":false,"showFog":true,"showSkybox":false,"showFlares":true,"showImageEffects":true,"showParticleSystems":true,"showVisualEffectGraphs":true,"m_FxEnabled":true},"in2DMode":false,"pivot":{"x":-1.600006103515625,"y":-48.394989013671878,"z":0.0},"rotation":{"x":-0.007498469203710556,"y":0.019498243927955629,"z":0.00014624613686464727,"w":0.9997819066047669},"size":154.0638885498047,"orthographic":false}