{"cameraMode":{"drawMode":0,"name":"Shaded","section":"Shading Mode"},"sceneLighting":true,"audioPlay":false,"sceneViewState":{"m_AlwaysRefresh":false,"showFog":true,"showSkybox":true,"showFlares":true,"showImageEffects":true,"showParticleSystems":true,"showVisualEffectGraphs":true,"m_FxEnabled":true},"in2DMode":false,"pivot":{"x":-1.274357557296753,"y":15.662519454956055,"z":31.490489959716798},"rotation":{"x":-0.20242515206336976,"y":-0.0991167202591896,"z":0.020601332187652589,"w":-0.9740608930587769},"size":38.2283821105957,"orthographic":true}