{"cameraMode":{"drawMode":0,"name":"Shaded","section":"Shading Mode"},"sceneLighting":false,"audioPlay":false,"sceneViewState":{"m_AlwaysRefresh":false,"showFog":true,"showSkybox":true,"showFlares":true,"showImageEffects":true,"showParticleSystems":true,"showVisualEffectGraphs":true,"m_FxEnabled":true},"in2DMode":false,"pivot":{"x":3.181652069091797,"y":2.104823112487793,"z":5.56418514251709},"rotation":{"x":0.16408708691596986,"y":0.13859029114246369,"z":-0.023290833458304406,"w":0.9763829708099365},"size":8.0454683303833,"orthographic":true}